pydango/__init__.py
pydango/connection/__init__.py
pydango/connection/client.py
pydango/connection/consts.py
pydango/connection/exceptions.py
pydango/connection/graph_utils.py
pydango/connection/query_utils.py
pydango/connection/session.py
pydango/connection/types.py
pydango/connection/utils.py
pydango/indexes.py
pydango/orm/__init__.py
pydango/orm/consts.py
pydango/orm/encoders.py
pydango/orm/models/__init__.py
pydango/orm/models/base.py
pydango/orm/models/edge.py
pydango/orm/models/fields.py
pydango/orm/models/relations.py
pydango/orm/models/sentinel.py
pydango/orm/models/shapes.py
pydango/orm/models/types.py
pydango/orm/models/utils.py
pydango/orm/models/vertex.py
pydango/orm/query.py
pydango/orm/utils.py
pydango/py.typed
pydango/query/__init__.py
pydango/query/consts.py
pydango/query/expressions.py
pydango/query/functions.py
pydango/query/operations.py
pydango/query/options.py
pydango/query/query.py
pydango/query/types.py
pydango/query/utils.py
pydango/utils.py
pydangorm-0.3.0.dist-info/LICENSE
pydangorm-0.3.0.dist-info/METADATA
pydangorm-0.3.0.dist-info/WHEEL
pydangorm-0.3.0.dist-info/RECORD
