Metadata-Version: 2.1
Name: pydangorm
Version: 0.3.0
Summary: pydantic based ArangoDB ODM
Home-page: https://github.com/nadobando/pydangorm
License: MIT
Author: nadobando
Author-email: 7695172+nadobando@users.noreply.github.com
Requires-Python: >=3.9,<4.0
Classifier: Framework :: Pydantic :: 1
Classifier: License :: OSI Approved :: MIT License
Classifier: Operating System :: OS Independent
Classifier: Programming Language :: Python
Classifier: Programming Language :: Python :: 3
Classifier: Programming Language :: Python :: 3.9
Classifier: Programming Language :: Python :: 3.10
Classifier: Programming Language :: Python :: 3.11
Classifier: Programming Language :: Python :: 3.10
Classifier: Programming Language :: Python :: 3.11
Classifier: Programming Language :: Python :: 3.12
Classifier: Programming Language :: Python :: 3.13
Classifier: Programming Language :: Python :: 3.8
Classifier: Programming Language :: Python :: 3.9
Classifier: Topic :: Database
Requires-Dist: aioarango (>=1.0.0,<2.0.0)
Requires-Dist: indexed (>=1.3.0,<2.0.0)
Requires-Dist: pydantic (>=1.10.17)
Requires-Dist: urllib3 (==1.26.15)
Project-URL: Documentation, https://nadobando.github.io/pydangorm
Project-URL: Repository, https://github.com/nadobando/pydangorm
